huntydata/__init__.py
huntydata/errors.py
huntydata/standardized.py
huntydata-0.2.0.dist-info/METADATA
huntydata-0.2.0.dist-info/WHEEL
huntydata-0.2.0.dist-info/top_level.txt
huntydata-0.2.0.dist-info/RECORD
